heliocats/__init__.py
heliocats/cats.py
heliocats/data.py
heliocats/plot.py
heliocats/stats.py
heliocats-1.2.1.dist-info/LICENSE
heliocats-1.2.1.dist-info/METADATA
heliocats-1.2.1.dist-info/WHEEL
heliocats-1.2.1.dist-info/top_level.txt
heliocats-1.2.1.dist-info/RECORD
