Metadata-Version: 2.1
Name: heliocats
Version: 1.2.1
Summary: Making heliospheric event catalogs
Home-page: https://github.com/cmoestl/heliocats
Author: Christian Moestl
Author-email: christian.moestl@oeaw.ac.at
License: UNKNOWN
Keywords: geophysics,heliophysics,space weather
Platform: UNKNOWN
Classifier: Programming Language :: Python :: 3
Classifier: License :: OSI Approved :: MIT License
Classifier: Operating System :: OS Independent
Requires-Python: >=3.7
License-File: LICENSE
